{
    "kurse" : {
      "mappings" : {
        "properties" : {
          "anzahl_termine" : {
            "type" : "text",
            "fields" : {
              "keyword" : {
                "type" : "keyword",
                "ignore_above" : 256
              }
            }
          },
          "beginn_datum" : {
            "type" : "date"
          },
          "dvv_kategorie" : {
            "properties" : {
              "#text" : {
                "type" : "text",
                "fields" : {
                  "keyword" : {
                    "type" : "keyword",
                    "ignore_above" : 256
                  }
                }
              },
              "@version" : {
                "type" : "text",
                "fields" : {
                  "keyword" : {
                    "type" : "keyword",
                    "ignore_above" : 256
                  }
                }
              }
            }
          },
          "ende_datum" : {
            "type" : "date"
          },
          "guid" : {
            "type" : "text",
            "fields" : {
              "keyword" : {
                "type" : "keyword",
                "ignore_above" : 256
              }
            }
          },
          "maximale_teilnehmerzahl" : {
            "type" : "text",
            "fields" : {
              "keyword" : {
                "type" : "keyword",
                "ignore_above" : 256
              }
            }
          },
          "minimale_teilnehmerzahl" : {
            "type" : "text",
            "fields" : {
              "keyword" : {
                "type" : "keyword",
                "ignore_above" : 256
              }
            }
          },
          "name" : {
            "type" : "text",
            "fields" : {
              "keyword" : {
                "type" : "keyword",
                "ignore_above" : 256
              }
            }
          },
          "nummer" : {
            "type" : "text",
            "fields" : {
              "keyword" : {
                "type" : "keyword",
                "ignore_above" : 256
              }
            }
          },
          "preis" : {
            "properties" : {
              "betrag" : {
                "type" : "text",
                "fields" : {
                  "keyword" : {
                    "type" : "keyword",
                    "ignore_above" : 256
                  }
                }
              },
              "rabatt_moeglich" : {
                "type" : "text",
                "fields" : {
                  "keyword" : {
                    "type" : "keyword",
                    "ignore_above" : 256
                  }
                }
              }
            }
          },
          "schlagwort" : {
            "type" : "text",
            "fields" : {
              "keyword" : {
                "type" : "keyword",
                "ignore_above" : 256
              }
            }
          },
          "text" : {
            "properties" : {
              "eigenschaft" : {
                "type" : "text",
                "fields" : {
                  "keyword" : {
                    "type" : "keyword",
                    "ignore_above" : 256
                  }
                }
              },
              "text" : {
                "type" : "text",
                "fields" : {
                  "keyword" : {
                    "type" : "keyword",
                    "ignore_above" : 256
                  }
                }
              }
            }
          },
          "untertitel" : {
            "type" : "text",
            "fields" : {
              "keyword" : {
                "type" : "keyword",
                "ignore_above" : 256
              }
            }
          },
          "veranstaltungsort" : {
            "properties" : {
              "adresse" : {
                "properties" : {
                  "land" : {
                    "type" : "text",
                    "fields" : {
                      "keyword" : {
                        "type" : "keyword",
                        "ignore_above" : 256
                      }
                    }
                  },
                  "ort" : {
                    "type" : "text",
                    "fields" : {
                      "keyword" : {
                        "type" : "keyword",
                        "ignore_above" : 256
                      }
                    }
                  },
                  "plz" : {
                    "type" : "text",
                    "fields" : {
                      "keyword" : {
                        "type" : "keyword",
                        "ignore_above" : 256
                      }
                    }
                  },
                  "strasse" : {
                    "type" : "text",
                    "fields" : {
                      "keyword" : {
                        "type" : "keyword",
                        "ignore_above" : 256
                      }
                    }
                  }
                }
              },
              "barrierefrei" : {
                "type" : "text",
                "fields" : {
                  "keyword" : {
                    "type" : "keyword",
                    "ignore_above" : 256
                  }
                }
              },
              "name" : {
                "type" : "text",
                "fields" : {
                  "keyword" : {
                    "type" : "keyword",
                    "ignore_above" : 256
                  }
                }
              }
            }
          },
          "webadresse" : {
            "properties" : {
              "name" : {
                "type" : "text",
                "fields" : {
                  "keyword" : {
                    "type" : "keyword",
                    "ignore_above" : 256
                  }
                }
              },
              "typ" : {
                "type" : "text",
                "fields" : {
                  "keyword" : {
                    "type" : "keyword",
                    "ignore_above" : 256
                  }
                }
              },
              "uri" : {
                "type" : "text",
                "fields" : {
                  "keyword" : {
                    "type" : "keyword",
                    "ignore_above" : 256
                  }
                }
              }
            }
          },
          "zielgruppe" : {
            "type" : "text",
            "fields" : {
              "keyword" : {
                "type" : "keyword",
                "ignore_above" : 256
              }
            }
          }
        }
      }
    }
  }  